conjugate_map/__init__.py
conjugate_map/conjCalcFunctions.py
conjugate_map/conj_calc.py
conjugate_map-0.3.0.dist-info/licenses/LICENSE
conjugate_map-0.3.0.dist-info/METADATA
conjugate_map-0.3.0.dist-info/WHEEL
conjugate_map-0.3.0.dist-info/top_level.txt
conjugate_map-0.3.0.dist-info/RECORD
