Metadata-Version: 2.4
Name: conjugate_map
Version: 0.3.0
Summary: Library for computing geomagnetic conjugate points.
Maintainer-email: "Kristina V. Collins" <kvcollins@spacescience.org>
License: MIT License
Project-URL: source, https://github.com/KCollins/conjugate_map
Project-URL: documentation, https://conjugate-map.readthedocs.io/en/latest
Project-URL: download, https://github.com/KCollins/conjugate_map/releases
Keywords: coordinates,ionosphere,atmosphere,thermosphere,magnetosphere,heliosphere,observations,models,analysis,conjugate,geomagnetic,instruments,mapping,visualization,plotting,Antarctica
Classifier: Development Status :: 3 - Alpha
Classifier: Intended Audience :: Science/Research
Classifier: Topic :: Scientific/Engineering :: Atmospheric Science
Classifier: Topic :: Scientific/Engineering :: Physics
Classifier: License :: OSI Approved :: MIT License
Classifier: Natural Language :: English
Classifier: Programming Language :: Python
Classifier: Programming Language :: Python :: 3
Classifier: Programming Language :: Python :: 3.9
Requires-Python: >=3.9
License-File: LICENSE
Requires-Dist: aacgmv2
Requires-Dist: geopack
Requires-Dist: gpxpy
Requires-Dist: numpy
Requires-Dist: pandas
Requires-Dist: plotly
Provides-Extra: test
Requires-Dist: coverage[toml]; extra == "test"
Requires-Dist: pylint; extra == "test"
Provides-Extra: apex
Requires-Dist: apexpy; extra == "apex"
Dynamic: license-file
